ntnucourses/__init__.py
ntnucourses/courses.py
ntnucourses-0.0.2.dist-info/LICENSE
ntnucourses-0.0.2.dist-info/METADATA
ntnucourses-0.0.2.dist-info/WHEEL
ntnucourses-0.0.2.dist-info/top_level.txt
ntnucourses-0.0.2.dist-info/RECORD
